nuralshell/__init__.py
nuralshell/cli.py
nuralshell/config.py
nuralshell-0.1.5.dist-info/METADATA
nuralshell-0.1.5.dist-info/WHEEL
nuralshell-0.1.5.dist-info/entry_points.txt
nuralshell-0.1.5.dist-info/top_level.txt
nuralshell-0.1.5.dist-info/RECORD
