Metadata-Version: 2.4
Name: nuralshell
Version: 0.1.5
Summary: A powerful CLI agent for system automation and file management.
Author-email: Sheikh Mujtaba <smujtabaja@email.com>
License: MIT
Project-URL: Homepage, https://github.com/Sheikh-Muhammad-Mujtaba/nuralshell
Keywords: ai,cli,agent,shell
Requires-Python: >=3.9
Requires-Dist: pydantic
Requires-Dist: openai-agents
Requires-Dist: asyncio
